sygnet/__init__.py
sygnet/blocks.py
sygnet/dataloaders.py
sygnet/experimental.py
sygnet/interface.py
sygnet/loader.py
sygnet/models.py
sygnet/requirements.py
sygnet/train.py
sygnet/tune.py
sygnet-0.0.13.dist-info/LICENSE
sygnet-0.0.13.dist-info/WHEEL
sygnet-0.0.13.dist-info/METADATA
sygnet-0.0.13.dist-info/RECORD
