Metadata-Version: 2.1
Name: sygnet
Version: 0.0.13
Summary: Synthetic data using Generative Adversarial Networks
Keywords: synthetic data,neural networks,GAN,torch
Author-email: Thomas Robinson <t.robinson7@lse.ac.uk>
Maintainer: Artem Nesterov, Maksim Zubok
Maintainer-email: Thomas Robinson <t.robinson7@lse.ac.uk>
Requires-Python: >=3.9
Classifier: Development Status :: 3 - Alpha
Classifier: Intended Audience :: Science/Research
Classifier: Topic :: Scientific/Engineering
Classifier: License :: OSI Approved :: GNU General Public License v3 (GPLv3)
Classifier: Programming Language :: Python :: 3
Classifier: Programming Language :: Python :: 3.9
Requires-Dist: numpy>=1.21
Requires-Dist: torch>=1.10.0
Requires-Dist: scikit-learn>=1.2
Requires-Dist: pandas>=1.4
Requires-Dist: tqdm
Requires-Dist: pickle ; extra == "save"
Requires-Dist: tensorboard ; extra == "viz"
Project-URL: Bugs, https://github.com/tsrobinson/SyGNet/issues
Project-URL: Source, https://github.com/tsrobinson/SyGNet
Provides-Extra: save
Provides-Extra: viz
